{
  "subtitle": "SPA Who shall I tell?", 
  "description": "D\u00edselo a tu doctor o a tu partera", 
  "language": "spa_ES", 
  "title": "\u00bfA qui\u00e9n se lo digo?", 
  "primary_category": "8bc4a31038864b1594918f7266dc4b7e", 
  "created_at": "2015-03-26T12:22:48+00:00", 
  "featured_in_category": false, 
  "modified_at": "2016-04-23T11:33:53.667714+00:00", 
  "_version": {
    "package_version": "1.0.1", 
    "language_version": "2.7.6", 
    "language_version_string": "2.7.6 (default, Mar 22 2014, 23:03:41) \n[GCC 4.8.2]", 
    "language": "python", 
    "package": "elastic-git"
  }, 
  "linked_pages": [
    "4be4cad84b8649fbb9df84fe0331db8c", 
    "77c7f9abdcb84fb7aac5746059fbf8a4", 
    "0d271f8c49bf41e59c0b95114a835a2c", 
    "482658b1663141548d3e46e7a302a9aa", 
    "48c54d10cebc4a46b4ed05fb73b6e8dd", 
    "441198eb525844629fbf7e06270b941b"
  ], 
  "id": null, 
  "content": "Creado por BabyCenter\r\n\r\nAlgunas mujeres quieren mantener su embarazo en secreto al principio. \r\n\r\nPero dec\u00edrselo a tu doctor no significa que tengas que dec\u00edrselo a todos los dem\u00e1s.\r\n\r\nHablar de estar embarazada con un doctor ser\u00e1 bueno para ti y para tu beb\u00e9. Habr\u00e1 menos problemas si obtienes la atenci\u00f3n que necesitas desde el principio.\r\n\r\nPuedes hacerte pruebas para asegurarte de que tu beb\u00e9 y t\u00fa est\u00e9n sanos. Puedes hacerte pruebas de orina, de sangre y de VIH. Si no te ofrecen las pruebas de VIH, puedes pedir que te hagan una.\r\n\r\nSi sabes que eres VIH+, acercate a tu doctor o asiste a la cl\u00ednica m\u00e1s cercana.\r\n\r\nIncluso si te sientes bien, ve a tus chequeos con regularidad para que t\u00fa y tu beb\u00e9 puedan seguir sanos.\r\n\r\n", 
  "source": "49d06467a46145c493239f286bb6fbe1", 
  "featured": false, 
  "author_tags": [], 
  "image": null, 
  "published": null, 
  "position": 50, 
  "image_host": "http://thumbor.unicore.io", 
  "slug": "spa-who-shall-i-tell", 
  "uuid": "2378f98a150c4a0882813a005635d6ba"
}